edge/README.md
edge/__init__.py
edge/admin.py
edge/assets.py
edge/blast.py
edge/blastdb.py
edge/context_processors.py
edge/crispr.py
edge/forms.py
edge/importer.py
edge/io.py
edge/orfs.py
edge/pcr.py
edge/primer.py
edge/recombine.py
edge/tasks.py
edge/urls.py
edge/utils.py
edge/views.py
edge/management/__init__.py
edge/management/commands/__init__.py
edge/management/commands/build_edge_blastdb.py
edge/management/commands/build_genome_blastdb.py
edge/management/commands/export_gff.py
edge/management/commands/import_gff.py
edge/management/commands/remove_fragment.py
edge/management/commands/remove_genome.py
edge/management/commands/tests.py
edge/migrations/0001_initial.py
edge/migrations/0002_auto_20220608_2010.py
edge/migrations/__init__.py
edge/models/__init__.py
edge/models/chunk.py
edge/models/fragment.py
edge/models/fragment_annotator.py
edge/models/fragment_updater.py
edge/models/fragment_writer.py
edge/models/genome.py
edge/models/genome_updater.py
edge/models/op.py
edge/south_migrations/0001_initial.py
edge/south_migrations/0002_auto__add_index_fragment_chunk_location_fragment_base_first__add_index.py
edge/south_migrations/0003_auto__chg_field_fragment_chunk_location_fragment__chg_field_fragment_c.py
edge/south_migrations/0004_auto__chg_field_genome_parent.py
edge/south_migrations/0005_auto__add_field_fragment_est_length.py
edge/south_migrations/0006_auto__add_fragment_index.py
edge/south_migrations/0007_auto__add_field_feature__qualifiers.py
edge/south_migrations/0008_auto__add_field_fragment_active__add_field_genome_active.py
edge/south_migrations/0009_auto__add_operation.py
edge/south_migrations/0010_auto__add_field_operation_params__chg_field_operation_type.py
edge/south_migrations/0011_auto__del_field_operation_fragment__add_field_feature_operation.py
edge/south_migrations/0012_auto__add_field_operation_genome.py
edge/south_migrations/0013_auto__del_field_operation_notes__add_field_genome_blastdb.py
edge_genome-3.28.2.dist-info/LICENSE.txt
edge_genome-3.28.2.dist-info/METADATA
edge_genome-3.28.2.dist-info/WHEEL
edge_genome-3.28.2.dist-info/top_level.txt
edge_genome-3.28.2.dist-info/zip-safe
edge_genome-3.28.2.dist-info/RECORD
