Metadata-Version: 2.1
Name: edge-genome
Version: 3.28.2
Summary: Genome Engineering Tool
Home-page: https://github.com/ginkgobioworks/edge/
Author: Ginkgo Bioworks
Author-email: devs@ginkgobioworks.com
License: MIT
Keywords: edge genome annotate track query django database ginkgo
Platform: UNKNOWN
Classifier: Development Status :: 5 - Production/Stable
Classifier: Environment :: Web Environment
Classifier: Environment :: Other Environment
Classifier: Framework :: Django :: 1.6
Classifier: Intended Audience :: Developers
Classifier: Intended Audience :: Science/Research
Classifier: License :: OSI Approved :: MIT License
Classifier: Natural Language :: English
Classifier: Operating System :: OS Independent
Classifier: Programming Language :: Python :: 2.7
Classifier: Programming Language :: JavaScript
Classifier: Programming Language :: SQL
Classifier: Topic :: Database
Classifier: Topic :: Internet :: WWW/HTTP :: Indexing/Search
Classifier: Topic :: Internet :: WWW/HTTP :: WSGI :: Application
Classifier: Topic :: Scientific/Engineering :: Artificial Intelligence
Classifier: Topic :: Scientific/Engineering :: Artificial Life
Classifier: Topic :: Scientific/Engineering :: Information Analysis
Classifier: Topic :: Software Development :: Libraries
Classifier: Topic :: Software Development :: Libraries :: Python Modules
Classifier: Topic :: Text Processing :: General
License-File: LICENSE.txt
Requires-Dist: django (~=2.2.13)
Requires-Dist: jsmin
Requires-Dist: celery (>=4.0)
Requires-Dist: bcbio-gff
Requires-Dist: pytz (>=1023b)
